seemps/__init__.py
seemps/expectation.py
seemps/hdf5.py
seemps/py.typed
seemps/qft.py
seemps/tools.py
seemps/typing.py
seemps/version.py
seemps/analysis/__init__.py
seemps/analysis/evaluation.py
seemps/analysis/evolution.py
seemps/analysis/factories.py
seemps/analysis/hdaf.py
seemps/analysis/interpolation.py
seemps/analysis/lagrange.py
seemps/analysis/mesh.py
seemps/analysis/operators.py
seemps/analysis/optimization.py
seemps/analysis/polynomials.py
seemps/analysis/sketching.py
seemps/analysis/space.py
seemps/analysis/comptree/__init__.py
seemps/analysis/comptree/binary.py
seemps/analysis/comptree/branch.py
seemps/analysis/comptree/chain.py
seemps/analysis/comptree/sparse_array.py
seemps/analysis/comptree/sparse_mps.py
seemps/analysis/cross/__init__.py
seemps/analysis/cross/black_box.py
seemps/analysis/cross/cross.py
seemps/analysis/cross/cross_dmrg.py
seemps/analysis/cross/cross_greedy.py
seemps/analysis/cross/cross_maxvol.py
seemps/analysis/derivatives/__init__.py
seemps/analysis/derivatives/finite_differences.py
seemps/analysis/derivatives/fourier_differentiation.py
seemps/analysis/expansion/__init__.py
seemps/analysis/expansion/chebyshev.py
seemps/analysis/expansion/expansion.py
seemps/analysis/expansion/legendre.py
seemps/analysis/integration/__init__.py
seemps/analysis/integration/integration.py
seemps/analysis/integration/mps_quadratures.py
seemps/analysis/integration/vector_quadratures.py
seemps/cython/__init__.py
seemps/cython/_contractions.py
seemps/cython/contractions.pxi
seemps/cython/core.cp312-win_amd64.pyd
seemps/cython/core.pyi
seemps/cython/core.pyx
seemps/cython/environments.pxi
seemps/cython/gemm.pxi
seemps/cython/schmidt.pxi
seemps/cython/svd.pxi
seemps/cython/truncation.pxi
seemps/evolution/__init__.py
seemps/evolution/arnoldi.py
seemps/evolution/common.py
seemps/evolution/crank_nicolson.py
seemps/evolution/euler.py
seemps/evolution/hdaf.py
seemps/evolution/radau.py
seemps/evolution/runge_kutta.py
seemps/evolution/tdvp.py
seemps-2.9.7.dist-info/licenses/LICENSE
seemps-2.9.7.dist-info/METADATA
seemps-2.9.7.dist-info/WHEEL
seemps-2.9.7.dist-info/top_level.txt
seemps-2.9.7.dist-info/RECORD
