Metadata-Version: 2.4
Name: seemps
Version: 2.9.7
Summary: Matrix Product State library for quantum simulation and numerical analysis
Author: Paula García Molina, Juan José Rodríguez aldavero
Author-email: Juan José García Ripoll <juanjose.garciaripoll@gmail.com>
Maintainer-email: Juan José García Ripoll <juanjose.garciaripoll@gmail.com>
License-Expression: MIT
Project-URL: Homepage, https://github.com/juanjosegarciaripoll/seemps2
Project-URL: Repository, https://github.com/juanjosegarciaripoll/seemps2
Project-URL: Documentation, https://seemps.readthedocs.io/
Project-URL: Bug Tracker, https://github.com/juanjosegarciaripoll/seemps2/issues
Project-URL: Changelog, https://github.com/juanjosegarciaripoll/seemps2/releases
Keywords: quantum-computing,matrix-product-states,tensor-networks,dmrg,numerical-analysis,quantum-simulation
Classifier: Development Status :: 4 - Beta
Classifier: Intended Audience :: Science/Research
Classifier: Operating System :: OS Independent
Classifier: Programming Language :: Python :: 3
Classifier: Programming Language :: Python :: 3.11
Classifier: Programming Language :: Python :: 3.12
Classifier: Programming Language :: Python :: 3.13
Classifier: Programming Language :: Python :: 3.14
Classifier: Topic :: Scientific/Engineering :: Physics
Classifier: Topic :: Scientific/Engineering :: Mathematics
Requires-Python: >=3.11
License-File: LICENSE
Requires-Dist: numpy
Requires-Dist: scipy
Requires-Dist: h5py
Provides-Extra: test
Requires-Dist: opt_einsum; extra == "test"
Dynamic: license-file
